flask_restplus/__about__.py
flask_restplus/__init__.py
flask_restplus/_http.py
flask_restplus/api.py
flask_restplus/apidoc.py
flask_restplus/cors.py
flask_restplus/errors.py
flask_restplus/fields.py
flask_restplus/inputs.py
flask_restplus/marshalling.py
flask_restplus/mask.py
flask_restplus/model.py
flask_restplus/namespace.py
flask_restplus/postman.py
flask_restplus/representations.py
flask_restplus/reqparse.py
flask_restplus/resource.py
flask_restplus/swagger.py
flask_restplus/utils.py
flask_restplus/schemas/__init__.py
flask_restplus/schemas/oas-2.0.json
flask_restplus/static/droid-sans.css
flask_restplus/static/favicon-16x16.png
flask_restplus/static/favicon-32x32.png
flask_restplus/static/swagger-ui-bundle.js
flask_restplus/static/swagger-ui-bundle.js.map
flask_restplus/static/swagger-ui-standalone-preset.js
flask_restplus/static/swagger-ui-standalone-preset.js.map
flask_restplus/static/swagger-ui.css
flask_restplus/static/swagger-ui.css.map
flask_restplus/static/swagger-ui.js
flask_restplus/static/swagger-ui.js.map
flask_restplus/static/files/.npmignore
flask_restplus/static/files/droid-sans-latin-400.woff
flask_restplus/static/files/droid-sans-latin-400.woff2
flask_restplus/static/files/droid-sans-latin-700.woff
flask_restplus/static/files/droid-sans-latin-700.woff2
flask_restplus/templates/swagger-ui-css.html
flask_restplus/templates/swagger-ui-libs.html
flask_restplus/templates/swagger-ui.html
flask_restplus_oauth_redirect-0.13.0.dist-info/AUTHORS.rst
flask_restplus_oauth_redirect-0.13.0.dist-info/LICENSE
flask_restplus_oauth_redirect-0.13.0.dist-info/METADATA
flask_restplus_oauth_redirect-0.13.0.dist-info/WHEEL
flask_restplus_oauth_redirect-0.13.0.dist-info/top_level.txt
flask_restplus_oauth_redirect-0.13.0.dist-info/RECORD
