Metadata-Version: 2.1
Name: flask-restplus-oauth-redirect
Version: 0.13.0
Summary: Fully featured framework for fast, easy and documented API development with Flask
Home-page: https://github.com/saibot94/flask-restplus
Author: Cristian Schuszter
Author-email: cristian.schuszter@cern.ch
License: BSD-3-Clause
Keywords: flask restplus rest api swagger openapi
Platform: UNKNOWN
Classifier: Development Status :: 3 - Alpha
Classifier: Programming Language :: Python
Classifier: Environment :: Web Environment
Classifier: Operating System :: OS Independent
Classifier: Intended Audience :: Developers
Classifier: Topic :: System :: Software Distribution
Classifier: Programming Language :: Python
Classifier: Programming Language :: Python :: 2
Classifier: Programming Language :: Python :: 2.7
Classifier: Programming Language :: Python :: 3
Classifier: Programming Language :: Python :: 3.4
Classifier: Programming Language :: Python :: 3.5
Classifier: Programming Language :: Python :: 3.6
Classifier: Programming Language :: Python :: Implementation :: PyPy
Classifier: Topic :: Software Development :: Libraries :: Python Modules
Classifier: License :: OSI Approved :: BSD License
Requires-Dist: aniso8601 (>=0.82)
Requires-Dist: jsonschema
Requires-Dist: Flask (>=0.8)
Requires-Dist: pytz
Requires-Dist: six (>=1.3.0)
Requires-Dist: enum34 ; python_version < "3.4"
Provides-Extra: doc
Requires-Dist: alabaster (==0.7.10) ; extra == 'doc'
Requires-Dist: Sphinx (==1.6.5) ; extra == 'doc'
Requires-Dist: sphinx-issues (==0.3.1) ; extra == 'doc'
Provides-Extra: test
Requires-Dist: blinker ; extra == 'test'
Requires-Dist: mock (==2.0.0) ; extra == 'test'
Requires-Dist: pytest (==3.2.3) ; extra == 'test'
Requires-Dist: pytest-benchmark (==3.1.1) ; extra == 'test'
Requires-Dist: pytest-cov (==2.5.1) ; extra == 'test'
Requires-Dist: pytest-faker (==2.0.0) ; extra == 'test'
Requires-Dist: pytest-flask (==0.10.0) ; extra == 'test'
Requires-Dist: pytest-mock (==1.6.3) ; extra == 'test'
Requires-Dist: pytest-profiling (==1.2.11) ; extra == 'test'
Requires-Dist: pytest-sugar (==0.9.0) ; extra == 'test'
Requires-Dist: tzlocal ; extra == 'test'
